nrcpy/__init__.py
nrcpy-1.2.3.dist-info/METADATA
nrcpy-1.2.3.dist-info/WHEEL
nrcpy-1.2.3.dist-info/top_level.txt
nrcpy-1.2.3.dist-info/RECORD
