Metadata-Version: 2.1
Name: nrcpy
Version: 1.2.3
Summary: A package for NRC devices
Home-page: https://github.com/Rebox98/nrcpy
Author: Hossein Ghaheri
Author-email: hosseinghaheri@yahoo.com
